JavaBianchengYaodian/README.md
JavaBianchengYaodian/__init__.py
JavaBianchengYaodian/__main__.py
JavaBianchengYaodian/file.epub
JavaBianchengYaodian/index.html
JavaBianchengYaodian/css/__init__.py
JavaBianchengYaodian/css/annotations.css
JavaBianchengYaodian/css/main.css
JavaBianchengYaodian/css/normalize.css
JavaBianchengYaodian/css/popup.css
JavaBianchengYaodian/font/__init__.py
JavaBianchengYaodian/font/fontello.eot
JavaBianchengYaodian/font/fontello.svg
JavaBianchengYaodian/font/fontello.ttf
JavaBianchengYaodian/font/fontello.woff
JavaBianchengYaodian/img/__init__.py
JavaBianchengYaodian/img/annotator-glyph-sprite.png
JavaBianchengYaodian/img/annotator-icon-sprite.png
JavaBianchengYaodian/img/apple-touch-icon.png
JavaBianchengYaodian/img/cancelfullscreen.png
JavaBianchengYaodian/img/close.png
JavaBianchengYaodian/img/fullscreen.png
JavaBianchengYaodian/img/loader.gif
JavaBianchengYaodian/img/menu-icon.png
JavaBianchengYaodian/img/save.png
JavaBianchengYaodian/img/saved.png
JavaBianchengYaodian/img/settings-s.png
JavaBianchengYaodian/img/settings.png
JavaBianchengYaodian/img/star.png
JavaBianchengYaodian/js/__init__.py
JavaBianchengYaodian/js/epub.js
JavaBianchengYaodian/js/epub.min.js
JavaBianchengYaodian/js/epub.min.map
JavaBianchengYaodian/js/hooks.min.js
JavaBianchengYaodian/js/hooks.min.map
JavaBianchengYaodian/js/reader.js
JavaBianchengYaodian/js/reader.js.map
JavaBianchengYaodian/js/reader.min.js
JavaBianchengYaodian/js/reader.min.map
JavaBianchengYaodian/js/hooks/__init__.py
JavaBianchengYaodian/js/hooks/extensions/__init__.py
JavaBianchengYaodian/js/hooks/extensions/highlight.js
JavaBianchengYaodian/js/libs/__init__.py
JavaBianchengYaodian/js/libs/jquery.min.js
JavaBianchengYaodian/js/libs/localforage.min.js
JavaBianchengYaodian/js/libs/screenfull.js
JavaBianchengYaodian/js/libs/screenfull.min.js
JavaBianchengYaodian/js/libs/zip.min.js
JavaBianchengYaodian/js/plugins/__init__.py
JavaBianchengYaodian/js/plugins/hypothesis.js
java_biancheng_yaodian-2024.3.1.0.dist-info/METADATA
java_biancheng_yaodian-2024.3.1.0.dist-info/WHEEL
java_biancheng_yaodian-2024.3.1.0.dist-info/entry_points.txt
java_biancheng_yaodian-2024.3.1.0.dist-info/top_level.txt
java_biancheng_yaodian-2024.3.1.0.dist-info/RECORD
